retry/__init__.py
retry/api.py
retry/compat.py
easyretry-0.9.4.dist-info/AUTHORS
easyretry-0.9.4.dist-info/LICENSE
easyretry-0.9.4.dist-info/METADATA
easyretry-0.9.4.dist-info/WHEEL
easyretry-0.9.4.dist-info/pbr.json
easyretry-0.9.4.dist-info/top_level.txt
easyretry-0.9.4.dist-info/RECORD
