Metadata-Version: 2.1
Name: easyretry
Version: 0.9.4
Summary: Easy to use retry decorator.
Home-page: https://github.com/luukkemp/easyretry
Author: luukkemp
Author-email: l.kemp@fullstaq.com
License: Apache License 2.0
Classifier: Development Status :: 4 - Beta
Classifier: Intended Audience :: Developers
Classifier: License :: OSI Approved :: Apache Software License
Classifier: Natural Language :: English
Classifier: Operating System :: OS Independent
Classifier: Programming Language :: Python
Classifier: Programming Language :: Python :: 2.6
Classifier: Programming Language :: Python :: 2.7
Classifier: Programming Language :: Python :: 3
Classifier: Programming Language :: Python :: 3.4
Classifier: Programming Language :: Python :: Implementation :: PyPy
Classifier: Topic :: Software Development
Requires-Python: >=2.6
License-File: LICENSE
License-File: AUTHORS
